panoramaTool/__init__.py
panoramaTool/__main__.py
panoramaTool/app.py
panoramaTool/logic/__init__.py
panoramaTool/logic/business_logic.py
panoramaTool/logic/csv_manager.py
panoramaTool/panorama_api/__init__.py
panoramaTool/panorama_api/address_groups_manager.py
panoramaTool/panorama_api/address_manager.py
panoramaTool/panorama_api/api_call.py
panoramaTool/panorama_api/api_request.py
panoramaTool/panorama_api/old_post_rules_manager.py
panoramaTool/panorama_api/post_rules.py
panoramaTool/panorama_api/post_rules_manager.py
panoramaTool/panorama_api/service.py
panoramaTool/panorama_api/service_groups_manager.py
panoramaTool/panorama_api/service_manager.py
panoramaTool/panorama_api/zones.py
panoramaTool/static/style.css
panoramaTool/templates/address_groups.html
panoramaTool/templates/addresses.html
panoramaTool/templates/base.html
panoramaTool/templates/form.html
panoramaTool/templates/groups.html
panoramaTool/templates/login.html
panoramaTool/templates/security_rules.html
panoramaTool/templates/service_groups.html
panoramaTool/templates/services.html
panoramaTool-0.1.15.dist-info/LICENSE
panoramaTool-0.1.15.dist-info/METADATA
panoramaTool-0.1.15.dist-info/WHEEL
panoramaTool-0.1.15.dist-info/top_level.txt
panoramaTool-0.1.15.dist-info/RECORD
